{ "columns":56,
 "image":"Premade_Character_05.png",
 "imageheight":656,
 "imagewidth":896,
 "margin":0,
 "name":"Premade_Character_05",
 "spacing":0,
 "tilecount":2296,
 "tiledversion":"1.8.5",
 "tileheight":16,
 "tiles":[
        {
         "animation":[
                {
                 "duration":200,
                 "tileid":1344
                }, 
                {
                 "duration":200,
                 "tileid":1345
                }, 
                {
                 "duration":200,
                 "tileid":1346
                }, 
                {
                 "duration":200,
                 "tileid":1347
                }, 
                {
                 "duration":200,
                 "tileid":1348
                }, 
                {
                 "duration":200,
                 "tileid":1349
                }, 
                {
                 "duration":200,
                 "tileid":1350
                }, 
                {
                 "duration":200,
                 "tileid":1351
                }, 
                {
                 "duration":200,
                 "tileid":1352
                }, 
                {
                 "duration":200,
                 "tileid":1353
                }, 
                {
                 "duration":200,
                 "tileid":1354
                }, 
                {
                 "duration":200,
                 "tileid":1355
                }, 
                {
                 "duration":200,
                 "tileid":1356
                }, 
                {
                 "duration":200,
                 "tileid":1357
                }],
         "id":1344,
         "type":"above"
        }, 
        {
         "animation":[
                {
                 "duration":200,
                 "tileid":1400
                }, 
                {
                 "duration":200,
                 "tileid":1401
                }, 
                {
                 "duration":200,
                 "tileid":1402
                }, 
                {
                 "duration":200,
                 "tileid":1403
                }, 
                {
                 "duration":200,
                 "tileid":1404
                }, 
                {
                 "duration":200,
                 "tileid":1405
                }, 
                {
                 "duration":200,
                 "tileid":1406
                }, 
                {
                 "duration":200,
                 "tileid":1407
                }, 
                {
                 "duration":200,
                 "tileid":1408
                }, 
                {
                 "duration":200,
                 "tileid":1409
                }, 
                {
                 "duration":200,
                 "tileid":1410
                }, 
                {
                 "duration":200,
                 "tileid":1411
                }, 
                {
                 "duration":200,
                 "tileid":1412
                }, 
                {
                 "duration":200,
                 "tileid":1413
                }],
         "id":1400,
         "objectgroup":
            {
             "draworder":"index",
             "id":2,
             "name":"",
             "objects":[
                    {
                     "height":16.1817818181818,
                     "id":1,
                     "name":"",
                     "rotation":0,
                     "type":"",
                     "visible":true,
                     "width":13,
                     "x":1.22727272727273,
                     "y":1.81818181825832e-05
                    }],
             "opacity":1,
             "type":"objectgroup",
             "visible":true,
             "x":0,
             "y":0
            }
        }],
 "tilewidth":16,
 "type":"tileset",
 "version":"1.8"
}